stac_insitu/__init__.py
stac_insitu/filter.py
stac_insitu/geometry.py
stac_insitu/io.py
stac_insitu/visualization.py
stac_insitu-0.1.0.dist-info/licenses/LICENSE
stac_insitu-0.1.0.dist-info/METADATA
stac_insitu-0.1.0.dist-info/WHEEL
stac_insitu-0.1.0.dist-info/top_level.txt
stac_insitu-0.1.0.dist-info/RECORD
