Metadata-Version: 2.4
Name: stac-insitu
Version: 0.1.0
License: Apache-2.0
Project-URL: Repository, https://github.com/IAOCEA/stac-insitu
Requires-Python: >=3.11
License-File: LICENSE
Requires-Dist: pystac
Requires-Dist: geopandas
Requires-Dist: movingpandas
Requires-Dist: pandas
Requires-Dist: shapely
Requires-Dist: toolz
Provides-Extra: visualization
Requires-Dist: folium; extra == "visualization"
Dynamic: license-file
